qt_range_slider/__init__.py
tests/__init__.py
tests/test_slider.py
qt_range_slider-0.4.2.dist-info/LICENSE
qt_range_slider-0.4.2.dist-info/METADATA
qt_range_slider-0.4.2.dist-info/WHEEL
qt_range_slider-0.4.2.dist-info/top_level.txt
qt_range_slider-0.4.2.dist-info/RECORD
