Metadata-Version: 2.1
Name: qt-range-slider
Version: 0.4.2
Summary: Qt widget-slider with two thumbs (min/max values)
Home-page: https://github.com/introkun/qt-range-slider
Author: Sergey G
Author-email: introkun@gmail.com
License: MIT
Classifier: License :: OSI Approved :: MIT License
Classifier: Operating System :: OS Independent
Classifier: Programming Language :: Python
Classifier: Programming Language :: Python :: 3
Classifier: Development Status :: 3 - Alpha
Requires-Python: >=3.9
License-File: LICENSE
Requires-Dist: PyQt6-Qt6
Requires-Dist: PyQt6-sip
